{
    "unknown": {
        "name": "未知..."
    },
    "jiangjh": {
        "name": "姜嘉骅",
        "image": "https://ghproxy.com/https://raw.githubusercontent.com/i-TechX/iTechX/file-base/people/images/jiangjh.jpg",
        "info": [
            ["envelope", "&#106;&#x69;&#97;&#110;&#x67;&#106;&#104;&#x40;&#115;&#104;&#97;&#x6e;&#103;&#104;&#97;&#105;&#x74;&#x65;&#99;&#104;&#46;&#101;&#100;&#117;&#46;&#99;&#110;", "mailto:&#106;&#x69;&#97;&#110;&#x67;&#106;&#104;&#x40;&#115;&#104;&#97;&#x6e;&#103;&#104;&#97;&#105;&#x74;&#x65;&#99;&#104;&#46;&#101;&#100;&#117;&#46;&#99;&#110;"],
            ["home", "Home Page", "https://sist.shanghaitech.edu.cn/2020/0707/c7499a58298/page.htm"]
        ],
        "teach-courses": [
            ["Spring", "2021", "SI120", "Discrete Mathematics"]
        ]
    },
    "zhanglf": {
        "name": "张良峰",
        "image": "https://ghproxy.com/https://raw.githubusercontent.com/i-TechX/iTechX/file-base/people/images/zhanglf.jpg",
        "info": [
            ["envelope", "&#122;&#x68;&#97;&#110;&#103;&#108;&#x66;&#64;&#115;&#x68;&#97;&#110;&#103;&#104;&#97;&#105;&#116;&#101;&#99;&#x68;&#x2e;&#x65;&#100;&#117;&#46;&#99;&#x6e;", "mailto:&#122;&#x68;&#97;&#110;&#103;&#108;&#x66;&#64;&#115;&#x68;&#97;&#110;&#103;&#104;&#97;&#105;&#116;&#101;&#99;&#x68;&#x2e;&#x65;&#100;&#117;&#46;&#99;&#x6e;"],
            ["home", "Home Page", "https://sist.shanghaitech.edu.cn/2020/0707/c7499a53860/page.htm"]
        ],
        "teach-courses": [
            ["Spring", "2020", "SI120", "Discrete Mathematics"],
            ["Spring", "2019", "SI120", "Discrete Mathematics"],
            ["Spring", "2018", "SI120", "Discrete Mathematics"],
            ["Spring", "2017", "SI120", "Discrete Mathematics"]
        ]
    },
    "lindsaynj": {
        "name": "Nicholas Lindsay",
        "info": [
            ["envelope", "&#108;&#105;&#x6e;&#100;&#115;&#97;&#121;&#110;&#106;&#64;&#115;&#104;&#97;&#110;&#103;&#104;&#97;&#105;&#116;&#101;&#99;&#104;&#46;&#101;&#100;&#117;&#46;&#x63;&#x6e;", "mailto:&#108;&#105;&#x6e;&#100;&#115;&#97;&#121;&#110;&#106;&#64;&#115;&#104;&#97;&#110;&#103;&#104;&#97;&#105;&#116;&#101;&#99;&#104;&#46;&#101;&#100;&#117;&#46;&#x63;&#x6e;"],
            ["home", "Home Page", "https://ims.shanghaitech.edu.cn/ims_en/2019/0306/c4742a40524/page.htm"]
        ],
        "teach-courses": [
            ["Spring", "2020", "SI120", "Discrete Mathematics"]
        ]
    },
    "nlegout": {
        "name": "Noémie Legout",
        "info": [
            ["envelope", "&#x6e;&#108;&#101;&#103;&#111;&#117;&#x74;&#64;&#115;&#104;&#97;&#x6e;&#103;&#x68;&#97;&#105;&#116;&#101;&#99;&#104;&#x2e;&#x65;&#100;&#x75;&#46;&#99;&#110;", "mailto:&#x6e;&#108;&#101;&#103;&#111;&#117;&#x74;&#64;&#115;&#104;&#97;&#x6e;&#103;&#x68;&#97;&#105;&#116;&#101;&#99;&#104;&#x2e;&#x65;&#100;&#x75;&#46;&#99;&#110;"],
            ["home", "Home Page", "https://ims.shanghaitech.edu.cn/2018/1110/c4741a35988/page.htm"]
        ],
        "teach-courses": [
            ["Spring", "2019", "SI120", "Discrete Mathematics"]
        ]
    },
    "tukw": {
        "name": "屠可伟",
        "image": "https://ghproxy.com/https://raw.githubusercontent.com/i-TechX/iTechX/file-base/people/images/tukw.jpg",
        "info": [
            ["envelope", "&#x74;&#117;&#107;&#x77;&#64;&#115;&#104;&#97;&#110;&#103;&#104;&#x61;&#105;&#116;&#101;&#99;&#104;&#46;&#101;&#100;&#x75;&#x2e;&#x63;&#110;", "mailto:&#x74;&#117;&#107;&#x77;&#64;&#115;&#104;&#97;&#110;&#103;&#104;&#x61;&#105;&#116;&#101;&#99;&#104;&#46;&#101;&#100;&#x75;&#x2e;&#x63;&#110;"],
            ["home", "Home Page", "https://faculty.sist.shanghaitech.edu.cn/faculty/tukw/"]
        ],
        "teach-courses": [
            ["Fall", "2021", "CS181", "Artificial Intelligence I"],
            ["Fall", "2020", "CS181", "Artificial Intelligence I"],
            ["Fall", "2019", "CS181", "Artificial Intelligence I"],
            ["Fall", "2018", "CS181", "Artificial Intelligence I"]
        ]
    },
    "hexm": {
        "name": "何旭明",
        "image": "https://ghproxy.com/https://raw.githubusercontent.com/i-TechX/iTechX/file-base/people/images/hexm.jpg",
        "info": [
            ["envelope", "&#104;&#101;&#120;&#x6d;&#x40;&#x73;&#104;&#97;&#110;&#103;&#104;&#97;&#105;&#x74;&#x65;&#99;&#104;&#46;&#x65;&#100;&#x75;&#46;&#99;&#110;", "mailto:&#104;&#101;&#120;&#x6d;&#x40;&#x73;&#104;&#97;&#110;&#103;&#104;&#97;&#105;&#x74;&#x65;&#99;&#104;&#46;&#x65;&#100;&#x75;&#46;&#99;&#110;"],
            ["home", "Home Page", "https://faculty.sist.shanghaitech.edu.cn/faculty/hexm/index.html"]
        ],
        "teach-courses": [
            ["Fall", "2020", "CS181", "Artificial Intelligence I"]
        ]
    },
    "wangyang4": {
        "name": "汪阳",
        "image": "https://ghproxy.com/https://raw.githubusercontent.com/i-TechX/iTechX/file-base/people/images/wangyang4.jpg",
        "info": [
            ["envelope", "&#119;&#97;&#110;&#103;&#121;&#97;&#x6e;&#103;&#52;&#64;&#x73;&#104;&#97;&#110;&#103;&#104;&#97;&#105;&#116;&#x65;&#99;&#104;&#46;&#x65;&#100;&#117;&#46;&#99;&#110;", "mailto:&#119;&#97;&#110;&#103;&#121;&#97;&#x6e;&#103;&#52;&#64;&#x73;&#104;&#97;&#110;&#103;&#104;&#97;&#105;&#116;&#x65;&#99;&#104;&#46;&#x65;&#100;&#117;&#46;&#99;&#110;"],
            ["home", "Home Page", "https://faculty.sist.shanghaitech.edu.cn/faculty/wangyang/web/people/yangwang.html"],
            ["flask", "Lab Page", "https://faculty.sist.shanghaitech.edu.cn/faculty/wangyang/"]
        ],
        "teach-courses": [
            ["Fall", "2021", "EE160", "Introduction to Control"],
            ["Fall", "2020", "EE160", "Introduction to Control"]
        ]
    },
    "borish": {
        "name": "Boris Houska",
        "image": "https://ghproxy.com/https://raw.githubusercontent.com/i-TechX/iTechX/file-base/people/images/borish.jpg",
        "info": [
            ["envelope", "&#x62;&#111;&#114;&#105;&#115;&#104;&#64;&#115;&#104;&#x61;&#110;&#x67;&#104;&#x61;&#x69;&#116;&#x65;&#x63;&#104;&#46;&#101;&#100;&#117;&#x2e;&#x63;&#110;", "mailto:&#x62;&#111;&#114;&#105;&#115;&#104;&#64;&#115;&#104;&#x61;&#110;&#x67;&#104;&#x61;&#x69;&#116;&#x65;&#x63;&#104;&#46;&#101;&#100;&#117;&#x2e;&#x63;&#110;"],
            ["home", "Home Page", "https://faculty.sist.shanghaitech.edu.cn/faculty/boris/"]
        ],
        "teach-courses": [
            ["Fall", "2020", "EE160", "Introduction to Control"],
            ["Fall", "2019", "EE160", "Introduction to Control"],
            ["Fall", "2018", "EE160", "Introduction to Control"],
            ["Fall", "2017", "EE160", "Introduction to Control"],
            ["Spring", "2017", "EE160", "Introduction to Control"]
        ]
    },
    "yinshu": {
        "name": "殷树",
        "image": "https://ghproxy.com/https://raw.githubusercontent.com/i-TechX/iTechX/file-base/people/images/yinshu.jpg",
        "info": [
            ["envelope", "&#121;&#105;&#110;&#115;&#104;&#117;&#64;&#115;&#104;&#x61;&#110;&#103;&#104;&#97;&#105;&#116;&#101;&#99;&#x68;&#46;&#101;&#100;&#117;&#46;&#99;&#110;", "mailto:&#121;&#105;&#110;&#115;&#104;&#117;&#64;&#115;&#104;&#x61;&#110;&#103;&#104;&#97;&#105;&#116;&#101;&#99;&#x68;&#46;&#101;&#100;&#117;&#46;&#99;&#110;"],
            ["home", "Home Page", "https://lion.sist.shanghaitech.edu.cn/people.html"],
            ["flask", "Lab Page", "https://lion.sist.shanghaitech.edu.cn/"]
        ],
        "teach-courses": [
            ["Fall", "2021", "CS130", "Operating Systems I"],
            ["Fall", "2020", "CS130", "Operating Systems I"],
            ["Fall", "2018", "CS130", "Operating Systems I"]
        ]
    },
    "xietao": {
        "name": "谢涛",
        "image": "https://ghproxy.com/https://raw.githubusercontent.com/i-TechX/iTechX/file-base/people/images/xietao.jpg",
        "info": [
            ["envelope", "&#x67;&#x61;&#x72;&#121;&#120;&#x69;&#101;&#x32;&#48;&#64;&#x79;&#97;&#x68;&#x6f;&#111;&#46;&#x63;&#111;&#109;", "mailto:&#x67;&#x61;&#x72;&#121;&#120;&#x69;&#101;&#x32;&#48;&#64;&#x79;&#97;&#x68;&#x6f;&#111;&#46;&#x63;&#111;&#109;"],
            ["home", "Home Page", "https://sist.shanghaitech.edu.cn/2020/0706/c7493a53774/page.htm"]
        ],
        "teach-courses": [
            ["Fall", "2019", "CS130", "Operating Systems I"]
        ]
    },
    "qiaowh": {
        "name": "乔文汇",
        "info": [
            ["envelope", "&#x71;&#105;&#x61;&#111;&#119;&#x68;&#64;&#115;&#104;&#97;&#110;&#103;&#x68;&#97;&#105;&#x74;&#x65;&#x63;&#104;&#46;&#x65;&#100;&#117;&#46;&#99;&#110;", "mailto:&#x71;&#105;&#x61;&#111;&#119;&#x68;&#64;&#115;&#104;&#97;&#110;&#103;&#x68;&#97;&#105;&#x74;&#x65;&#x63;&#104;&#46;&#x65;&#100;&#117;&#46;&#99;&#110;"]
        ],
        "ta-courses": [
            ["Spring", "2021", "SI120", "Discrete Mathematics"],
            ["Fall", "2020", "CS181", "Artificial Intelligence I"],
            ["Spring", "2020", "SI120", "Discrete Mathematics"]
        ]
    },
    "xuzhl2": {
        "name": "徐钟灵",
        "info": [
            ["envelope", "&#120;&#117;&#122;&#104;&#108;&#x32;&#64;&#115;&#104;&#97;&#x6e;&#103;&#104;&#x61;&#x69;&#x74;&#101;&#99;&#104;&#46;&#101;&#100;&#117;&#46;&#99;&#110;", "mailto:&#120;&#117;&#122;&#104;&#108;&#x32;&#64;&#115;&#104;&#97;&#x6e;&#103;&#104;&#x61;&#x69;&#x74;&#101;&#99;&#104;&#46;&#101;&#100;&#117;&#46;&#99;&#110;"]
        ],
        "ta-courses": [
            ["Spring", "2021", "SI120", "Discrete Mathematics"]
        ]
    },
    "wuhy1": {
        "name": "吴昊一",
        "info": [
            ["envelope", "&#119;&#x75;&#104;&#x79;&#49;&#64;&#x73;&#x68;&#x61;&#x6e;&#103;&#104;&#97;&#x69;&#116;&#x65;&#99;&#104;&#46;&#101;&#100;&#x75;&#46;&#99;&#110;", "mailto:&#119;&#x75;&#104;&#x79;&#49;&#64;&#x73;&#x68;&#x61;&#x6e;&#103;&#104;&#97;&#x69;&#116;&#x65;&#99;&#104;&#46;&#101;&#100;&#x75;&#46;&#99;&#110;"]
        ],
        "ta-courses": [
            ["Fall", "2021", "CS181", "Artificial Intelligence I"],
            ["Spring", "2021", "SI120", "Discrete Mathematics"],
            ["Fall", "2020", "CS181", "Artificial Intelligence I"],
            ["Spring", "2020", "SI120", "Discrete Mathematics"]
        ]
    },
    "lizha": {
        "name": "李卓安",
        "info": [
            ["envelope", "&#108;&#105;&#122;&#104;&#97;&#x40;&#115;&#104;&#97;&#x6e;&#103;&#104;&#x61;&#x69;&#x74;&#101;&#99;&#x68;&#46;&#101;&#100;&#117;&#x2e;&#x63;&#x6e;", "mailto:&#108;&#105;&#122;&#104;&#97;&#x40;&#115;&#104;&#97;&#x6e;&#103;&#104;&#x61;&#x69;&#x74;&#101;&#99;&#x68;&#46;&#101;&#100;&#117;&#x2e;&#x63;&#x6e;"]
        ],
        "ta-courses": [
            ["Spring", "2021", "SI120", "Discrete Mathematics"]
        ]
    },
    "youch": {
        "name": "尤存翰",
        "info": [
            ["envelope", "&#121;&#111;&#117;&#99;&#x68;&#64;&#x73;&#104;&#97;&#110;&#103;&#104;&#97;&#x69;&#116;&#101;&#x63;&#104;&#x2e;&#x65;&#100;&#117;&#46;&#x63;&#x6e;", "mailto:&#121;&#111;&#117;&#99;&#x68;&#64;&#x73;&#104;&#97;&#110;&#103;&#104;&#97;&#x69;&#116;&#101;&#x63;&#104;&#x2e;&#x65;&#100;&#117;&#46;&#x63;&#x6e;"]
        ],
        "ta-courses": [
            ["Fall", "2021", "CS130", "Operating Systems I"],
            ["Spring", "2021", "SI120", "Discrete Mathematics"],
            ["Spring", "2020", "SI120", "Discrete Mathematics"]
        ]
    },
    "zhuqy": {
        "name": "祝青杨",
        "info": [
            ["envelope", "&#122;&#x68;&#117;&#x71;&#121;&#x40;&#115;&#104;&#97;&#x6e;&#103;&#104;&#97;&#105;&#116;&#x65;&#x63;&#104;&#46;&#x65;&#100;&#117;&#x2e;&#x63;&#110;", "mailto:&#122;&#x68;&#117;&#x71;&#121;&#x40;&#115;&#104;&#97;&#x6e;&#103;&#104;&#97;&#105;&#116;&#x65;&#x63;&#104;&#46;&#x65;&#100;&#117;&#x2e;&#x63;&#110;"]
        ],
        "ta-courses": [
            ["Spring", "2021", "SI120", "Discrete Mathematics"]
        ]
    },
    "mayx2": {
        "name": "马雅鑫",
        "info": [
            ["envelope", "&#109;&#97;&#121;&#x78;&#50;&#x40;&#115;&#104;&#x61;&#110;&#103;&#104;&#97;&#x69;&#116;&#101;&#99;&#x68;&#46;&#101;&#100;&#117;&#46;&#99;&#110;", "mailto:&#109;&#97;&#121;&#x78;&#50;&#x40;&#115;&#104;&#x61;&#110;&#103;&#104;&#97;&#x69;&#116;&#101;&#99;&#x68;&#46;&#101;&#100;&#117;&#46;&#99;&#110;"]
        ],
        "ta-courses": [
            ["Spring", "2021", "SI120", "Discrete Mathematics"]
        ]
    },
    "kepzh": {
        "name": "柯鹏震",
        "info": [
            ["envelope", "&#107;&#101;&#112;&#x7a;&#104;&#x40;&#x73;&#104;&#97;&#110;&#103;&#x68;&#x61;&#105;&#116;&#101;&#99;&#104;&#x2e;&#101;&#100;&#117;&#46;&#99;&#110;", "mailto:&#107;&#101;&#112;&#x7a;&#104;&#x40;&#x73;&#104;&#97;&#110;&#103;&#x68;&#x61;&#105;&#116;&#101;&#99;&#104;&#x2e;&#101;&#100;&#117;&#46;&#99;&#110;"]
        ],
        "ta-courses": [
            ["Spring", "2020", "SI120", "Discrete Mathematics"]
        ]
    },
    "zengli": {
        "name": "曾理",
        "info": [
            ["envelope", "&#122;&#101;&#110;&#103;&#108;&#x69;&#64;&#x73;&#104;&#x61;&#110;&#103;&#104;&#97;&#105;&#116;&#101;&#x63;&#104;&#46;&#x65;&#x64;&#117;&#46;&#99;&#110;", "mailto:&#122;&#101;&#110;&#103;&#108;&#x69;&#64;&#x73;&#104;&#x61;&#110;&#103;&#104;&#97;&#105;&#116;&#101;&#x63;&#104;&#46;&#x65;&#x64;&#117;&#46;&#99;&#110;"]
        ],
        "ta-courses": [
            ["Spring", "2020", "SI120", "Discrete Mathematics"]
        ]
    },
    "xiasa": {
        "name": "夏苏安",
        "info": [
            ["envelope", "&#120;&#105;&#x61;&#115;&#x61;&#64;&#115;&#104;&#x61;&#110;&#103;&#104;&#97;&#105;&#x74;&#101;&#99;&#x68;&#46;&#101;&#x64;&#x75;&#46;&#99;&#110;", "mailto:&#120;&#105;&#x61;&#115;&#x61;&#64;&#115;&#104;&#x61;&#110;&#103;&#104;&#97;&#105;&#x74;&#101;&#99;&#x68;&#46;&#101;&#x64;&#x75;&#46;&#99;&#110;"]
        ],
        "ta-courses": [
            ["Spring", "2020", "SI120", "Discrete Mathematics"]
        ]
    },
    "chenzhuo": {
        "name": "陈卓",
        "info": [
            ["envelope", "&#99;&#x68;&#x65;&#110;&#122;&#104;&#117;&#111;&#64;&#115;&#104;&#97;&#110;&#103;&#104;&#97;&#105;&#116;&#101;&#99;&#104;&#46;&#101;&#100;&#117;&#x2e;&#x63;&#110;", "mailto:&#99;&#x68;&#x65;&#110;&#122;&#104;&#117;&#111;&#64;&#115;&#104;&#97;&#110;&#103;&#104;&#97;&#105;&#116;&#101;&#99;&#104;&#46;&#101;&#100;&#117;&#x2e;&#x63;&#110;"]
        ],
        "ta-courses": [
            ["Fall", "2021", "CS181", "Artificial Intelligence I"]
        ]
    },
    "yangsl": {
        "name": "杨松霖",
        "info": [
            ["envelope", "&#121;&#97;&#110;&#103;&#115;&#108;&#64;&#x73;&#104;&#97;&#110;&#103;&#104;&#97;&#105;&#116;&#x65;&#99;&#104;&#x2e;&#101;&#100;&#117;&#46;&#99;&#110;", "mailto:&#121;&#97;&#110;&#103;&#115;&#108;&#64;&#x73;&#104;&#97;&#110;&#103;&#104;&#97;&#105;&#116;&#x65;&#99;&#104;&#x2e;&#101;&#100;&#117;&#46;&#99;&#110;"]
        ],
        "ta-courses": [
            ["Fall", "2021", "CS181", "Artificial Intelligence I"]
        ]
    },
    "chents": {
        "name": "陈天素",
        "info": [
            ["envelope", "&#99;&#x68;&#x65;&#110;&#116;&#115;&#x40;&#115;&#104;&#x61;&#110;&#103;&#104;&#97;&#x69;&#x74;&#101;&#x63;&#104;&#46;&#x65;&#100;&#x75;&#46;&#99;&#110;", "mailto:&#99;&#x68;&#x65;&#110;&#116;&#115;&#x40;&#115;&#104;&#x61;&#110;&#103;&#104;&#97;&#x69;&#x74;&#101;&#x63;&#104;&#46;&#x65;&#100;&#x75;&#46;&#99;&#110;"]
        ],
        "ta-courses": [
            ["Fall", "2021", "CS181", "Artificial Intelligence I"]
        ]
    },
    "jiangchy": {
        "name": "蒋承越",
        "image": "https://ghproxy.com/https://raw.githubusercontent.com/i-TechX/iTechX/file-base/people/images/jiangchy.jpg",
        "info": [
            ["envelope", "&#106;&#x69;&#97;&#110;&#103;&#x63;&#x68;&#121;&#64;&#115;&#x68;&#x61;&#110;&#x67;&#104;&#97;&#105;&#116;&#101;&#99;&#104;&#46;&#101;&#100;&#117;&#46;&#99;&#x6e;", "mailto:&#106;&#x69;&#97;&#110;&#103;&#x63;&#x68;&#121;&#64;&#115;&#x68;&#x61;&#110;&#x67;&#104;&#97;&#105;&#116;&#101;&#99;&#104;&#46;&#101;&#100;&#117;&#46;&#99;&#x6e;"],
            ["home", "Home Page", "https://jeffchy.github.io/"]
        ],
        "ta-courses": [
            ["Fall", "2020", "CS181", "Artificial Intelligence I"],
            ["Fall", "2019", "CS181", "Artificial Intelligence I"]
        ]
    },
    "jiazx": {
        "name": "贾子夏",
        "info": [
            ["envelope", "&#106;&#105;&#x61;&#122;&#120;&#x40;&#115;&#104;&#97;&#110;&#103;&#104;&#97;&#x69;&#116;&#x65;&#x63;&#104;&#46;&#101;&#x64;&#x75;&#46;&#99;&#110;", "mailto:&#106;&#105;&#x61;&#122;&#120;&#x40;&#115;&#104;&#97;&#110;&#103;&#104;&#97;&#x69;&#116;&#x65;&#x63;&#104;&#46;&#101;&#x64;&#x75;&#46;&#99;&#110;"]
        ],
        "ta-courses": [
            ["Fall", "2020", "CS181", "Artificial Intelligence I"]
        ]
    },
    "chendh1": {
        "name": "陈德弘",
        "info": [
            ["envelope", "&#99;&#104;&#101;&#110;&#100;&#104;&#49;&#64;&#115;&#104;&#97;&#110;&#103;&#104;&#97;&#105;&#x74;&#101;&#99;&#104;&#46;&#101;&#x64;&#117;&#46;&#99;&#110;", "mailto:&#99;&#104;&#101;&#110;&#100;&#104;&#49;&#64;&#115;&#104;&#97;&#110;&#103;&#104;&#97;&#105;&#x74;&#101;&#99;&#104;&#46;&#101;&#x64;&#117;&#46;&#99;&#110;"]
        ],
        "ta-courses": [
            ["Fall", "2020", "CS181", "Artificial Intelligence I"]
        ]
    },
    "zhanggl1": {
        "name": "张甘霖",
        "image": "https://ghproxy.com/https://raw.githubusercontent.com/i-TechX/iTechX/file-base/people/images/zhanggl1.jpg",
        "info": [
            ["envelope", "&#122;&#104;&#97;&#110;&#103;&#103;&#108;&#49;&#x40;&#115;&#104;&#x61;&#x6e;&#103;&#104;&#97;&#x69;&#116;&#101;&#x63;&#104;&#46;&#x65;&#x64;&#117;&#x2e;&#99;&#110;", "mailto:&#122;&#104;&#97;&#110;&#103;&#103;&#108;&#49;&#x40;&#115;&#104;&#x61;&#x6e;&#103;&#104;&#97;&#x69;&#116;&#101;&#x63;&#104;&#46;&#x65;&#x64;&#117;&#x2e;&#99;&#110;"]
        ],
        "ta-courses": [
            ["Fall", "2020", "CS181", "Artificial Intelligence I"]
        ]
    },
    "huzch": {
        "name": "胡泽川",
        "info": [
            ["envelope", "&#x68;&#x75;&#122;&#99;&#104;&#64;&#115;&#x68;&#x61;&#110;&#103;&#104;&#97;&#105;&#116;&#x65;&#99;&#104;&#x2e;&#x65;&#100;&#117;&#46;&#99;&#110;", "mailto:&#x68;&#x75;&#122;&#99;&#104;&#64;&#115;&#x68;&#x61;&#110;&#103;&#104;&#97;&#105;&#116;&#x65;&#99;&#104;&#x2e;&#x65;&#100;&#117;&#46;&#99;&#110;"]
        ],
        "ta-courses": [
            ["Fall", "2019", "CS181", "Artificial Intelligence I"]
        ]
    },
    "shenyao": {
        "name": "沈尧",
        "ta-courses": [
            ["Fall", "2019", "CS181", "Artificial Intelligence I"]
        ]
    },
    "caoyf": {
        "name": "曹逸凡",
        "ta-courses": [
            ["Fall", "2019", "CS181", "Artificial Intelligence I"]
        ]
    },
    "dengbw": {
        "name": "邓博文",
        "ta-courses": [
            ["Fall", "2019", "CS181", "Artificial Intelligence I"]
        ]
    },
    "yuxp": {
        "name": "余肖鹏",
        "image": "https://ghproxy.com/https://raw.githubusercontent.com/i-TechX/iTechX/file-base/people/images/yuxp.jpg",
        "info": [
            ["envelope", "&#121;&#x75;&#120;&#112;&#64;&#115;&#104;&#97;&#110;&#103;&#x68;&#97;&#105;&#116;&#101;&#99;&#104;&#x2e;&#101;&#100;&#x75;&#x2e;&#99;&#110;", "mailto:&#121;&#x75;&#120;&#112;&#64;&#115;&#104;&#97;&#110;&#103;&#x68;&#97;&#105;&#116;&#101;&#99;&#104;&#x2e;&#101;&#100;&#x75;&#x2e;&#99;&#110;"]
        ],
        "ta-courses": [
            ["Fall", "2021", "EE160", "Introduction to Control"]
        ]
    },
    "hegq": {
        "name": "贺贯齐",
        "info": [
            ["envelope", "&#104;&#101;&#103;&#113;&#x40;&#115;&#x68;&#x61;&#110;&#103;&#104;&#x61;&#x69;&#116;&#101;&#99;&#x68;&#46;&#101;&#100;&#117;&#46;&#99;&#110;", "mailto:&#104;&#101;&#103;&#113;&#x40;&#115;&#x68;&#x61;&#110;&#103;&#104;&#x61;&#x69;&#116;&#101;&#99;&#x68;&#46;&#101;&#100;&#117;&#46;&#99;&#110;"]
        ],
        "ta-courses": [
            ["Fall", "2021", "EE160", "Introduction to Control"]
        ]
    },
    "panyq": {
        "name": "潘宇琦",
        "info": [
            ["envelope", "&#x70;&#97;&#110;&#121;&#113;&#64;&#115;&#x68;&#97;&#110;&#103;&#104;&#x61;&#x69;&#x74;&#101;&#99;&#104;&#46;&#101;&#x64;&#117;&#x2e;&#99;&#110;", "mailto:&#x70;&#97;&#110;&#121;&#113;&#64;&#115;&#x68;&#97;&#110;&#103;&#104;&#x61;&#x69;&#x74;&#101;&#99;&#104;&#46;&#101;&#x64;&#117;&#x2e;&#99;&#110;"]
        ],
        "ta-courses": [
            ["Fall", "2021", "EE160", "Introduction to Control"]
        ]
    },
    "zhangheng1": {
        "name": "张恒",
        "info": [
            ["envelope", "&#122;&#x68;&#97;&#110;&#103;&#104;&#x65;&#110;&#103;&#x31;&#64;&#115;&#104;&#97;&#110;&#103;&#x68;&#x61;&#105;&#116;&#x65;&#99;&#x68;&#46;&#101;&#100;&#117;&#46;&#99;&#x6e;", "mailto:&#122;&#x68;&#97;&#110;&#103;&#104;&#x65;&#110;&#103;&#x31;&#64;&#115;&#104;&#97;&#110;&#103;&#x68;&#x61;&#105;&#116;&#x65;&#99;&#x68;&#46;&#101;&#100;&#117;&#46;&#99;&#x6e;"]
        ],
        "ta-courses": [
            ["Fall", "2021", "EE160", "Introduction to Control"]
        ]
    },
    "duxu": {
        "name": "杜旭",
        "info": [
            ["envelope", "&#100;&#117;&#x78;&#117;&#64;&#115;&#104;&#97;&#110;&#103;&#104;&#97;&#105;&#x74;&#101;&#99;&#104;&#46;&#101;&#x64;&#x75;&#46;&#99;&#110;", "mailto:&#100;&#117;&#x78;&#117;&#64;&#115;&#104;&#97;&#110;&#103;&#104;&#97;&#105;&#x74;&#101;&#99;&#104;&#46;&#101;&#x64;&#x75;&#46;&#99;&#110;"]
        ],
        "ta-courses": [
            ["Fall", "2020", "EE160", "Introduction to Control"]
        ]
    },
    "guoyx1": {
        "name": "郭宇璇",
        "info": [
            ["envelope", "&#103;&#117;&#111;&#121;&#x78;&#49;&#64;&#x73;&#x68;&#97;&#x6e;&#103;&#104;&#97;&#105;&#116;&#101;&#99;&#104;&#x2e;&#101;&#100;&#117;&#46;&#x63;&#110;", "mailto:&#103;&#117;&#111;&#121;&#x78;&#49;&#64;&#x73;&#x68;&#97;&#x6e;&#103;&#104;&#97;&#105;&#116;&#101;&#99;&#104;&#x2e;&#101;&#100;&#117;&#46;&#x63;&#110;"]
        ],
        "ta-courses": [
            ["Fall", "2020", "EE160", "Introduction to Control"]
        ]
    },
    "lijl": {
        "name": "李家纶",
        "ta-courses": [
            ["Fall", "2020", "EE160", "Introduction to Control"]
        ]
    },
    "limzh": {
        "name": "李敏章",
        "image": "https://ghproxy.com/https://raw.githubusercontent.com/i-TechX/iTechX/file-base/people/images/limzh.jpg",
        "info": [
            ["envelope", "&#108;&#105;&#x6d;&#x7a;&#104;&#64;&#115;&#104;&#97;&#110;&#103;&#104;&#97;&#x69;&#116;&#101;&#99;&#104;&#x2e;&#x65;&#100;&#117;&#46;&#99;&#110;", "mailto:&#108;&#105;&#x6d;&#x7a;&#104;&#64;&#115;&#104;&#97;&#110;&#103;&#104;&#97;&#x69;&#116;&#101;&#99;&#104;&#x2e;&#x65;&#100;&#117;&#46;&#99;&#110;"]
        ],
        "ta-courses": [
            ["Fall", "2021", "CS130", "Operating Systems I"]
        ]
    },
    "zhaochf": {
        "name": "赵乘风",
        "image": "https://ghproxy.com/https://raw.githubusercontent.com/i-TechX/iTechX/file-base/people/images/zhaochf.jpg",
        "info": [
            ["envelope", "&#122;&#104;&#97;&#111;&#x63;&#104;&#102;&#64;&#115;&#104;&#97;&#110;&#103;&#104;&#x61;&#105;&#x74;&#101;&#99;&#104;&#x2e;&#101;&#100;&#x75;&#x2e;&#99;&#110;", "mailto:&#122;&#104;&#97;&#111;&#x63;&#104;&#102;&#64;&#115;&#104;&#97;&#110;&#103;&#104;&#x61;&#105;&#x74;&#101;&#99;&#104;&#x2e;&#101;&#100;&#x75;&#x2e;&#99;&#110;"]
        ],
        "ta-courses": [
            ["Fall", "2021", "CS130", "Operating Systems I"]
        ]
    },
    "ligch": {
        "name": "李冠呈",
        "image": "https://ghproxy.com/https://raw.githubusercontent.com/i-TechX/iTechX/file-base/people/images/ligch.jpg",
        "info": [
            ["envelope", "&#108;&#105;&#103;&#x63;&#104;&#64;&#115;&#104;&#97;&#x6e;&#103;&#104;&#97;&#105;&#116;&#101;&#99;&#104;&#46;&#101;&#100;&#x75;&#46;&#99;&#110;", "mailto:&#108;&#105;&#103;&#x63;&#104;&#64;&#115;&#104;&#97;&#x6e;&#103;&#104;&#97;&#105;&#116;&#101;&#99;&#104;&#46;&#101;&#100;&#x75;&#46;&#99;&#110;"]
        ],
        "ta-courses": [
            ["Fall", "2021", "CS130", "Operating Systems I"]
        ]
    },
    "danghr": {
        "name": "党浩然",
        "info": [
            ["envelope", "&#100;&#x61;&#110;&#103;&#104;&#114;&#64;&#115;&#x68;&#x61;&#x6e;&#103;&#104;&#97;&#x69;&#x74;&#101;&#99;&#x68;&#46;&#101;&#x64;&#117;&#46;&#99;&#x6e;", "mailto:&#100;&#x61;&#110;&#103;&#104;&#114;&#64;&#115;&#x68;&#x61;&#x6e;&#103;&#104;&#97;&#x69;&#x74;&#101;&#99;&#x68;&#46;&#101;&#x64;&#117;&#46;&#99;&#x6e;"]
        ],
        "ta-courses": [
            ["Fall", "2021", "CS130", "Operating Systems I"]
        ]
    },
    "zhangzhch2": {
        "name": "张之辰",
        "info": [
            ["envelope", "&#122;&#x68;&#97;&#110;&#103;&#122;&#x68;&#99;&#104;&#50;&#x40;&#115;&#104;&#97;&#x6e;&#103;&#104;&#97;&#105;&#116;&#101;&#99;&#104;&#46;&#x65;&#100;&#117;&#46;&#x63;&#110;", "mailto:&#122;&#x68;&#97;&#110;&#103;&#122;&#x68;&#99;&#104;&#50;&#x40;&#115;&#104;&#97;&#x6e;&#103;&#104;&#97;&#105;&#116;&#101;&#99;&#104;&#46;&#x65;&#100;&#117;&#46;&#x63;&#110;"]
        ],
        "ta-courses": [
            ["Fall", "2021", "CS130", "Operating Systems I"]
        ]
    },
    "songyj": {
        "name": "宋延杰",
        "image": "https://ghproxy.com/https://raw.githubusercontent.com/i-TechX/iTechX/file-base/people/images/songyj.jpg",
        "info": [
            ["envelope", "&#115;&#x6f;&#110;&#x67;&#x79;&#x6a;&#x40;&#x73;&#104;&#97;&#x6e;&#103;&#x68;&#97;&#x69;&#116;&#x65;&#99;&#104;&#46;&#101;&#100;&#x75;&#46;&#99;&#x6e;", "mailto:&#115;&#x6f;&#110;&#x67;&#x79;&#x6a;&#x40;&#x73;&#104;&#97;&#x6e;&#103;&#x68;&#97;&#x69;&#116;&#x65;&#99;&#104;&#46;&#101;&#100;&#x75;&#46;&#99;&#x6e;"]
        ],
        "ta-courses": [
            ["Fall", "2020", "CS130", "Operating Systems I"],
            ["Fall", "2019", "CS130", "Operating Systems I"],
            ["Fall", "2018", "CS130", "Operating Systems I"]
        ]
    },
    "zhangqh": {
        "name": "张起豪",
        "image": "https://ghproxy.com/https://raw.githubusercontent.com/i-TechX/iTechX/file-base/people/images/zhangqh.jpg",
        "info": [
            ["envelope", "&#122;&#x68;&#x61;&#x6e;&#103;&#113;&#104;&#x40;&#x73;&#x68;&#97;&#x6e;&#x67;&#x68;&#97;&#x69;&#x74;&#x65;&#x63;&#x68;&#x2e;&#x65;&#100;&#117;&#x2e;&#x63;&#110;", "mailto:&#122;&#x68;&#x61;&#x6e;&#103;&#113;&#104;&#x40;&#x73;&#x68;&#97;&#x6e;&#x67;&#x68;&#97;&#x69;&#x74;&#x65;&#x63;&#x68;&#x2e;&#x65;&#100;&#117;&#x2e;&#x63;&#110;"]       
        ],
        "ta-courses": [
            ["Fall", "2020", "CS130", "Operating Systems I"],
            ["Fall", "2019", "CS130", "Operating Systems I"],
            ["Fall", "2018", "CS130", "Operating Systems I"]
        ]
    },
    "linzhy": {
        "name": "林仲岳",
        "image": "https://ghproxy.com/https://raw.githubusercontent.com/i-TechX/iTechX/file-base/people/images/linzhy.jpg",
        "info": [
            ["envelope", "&#x6c;&#x69;&#x6e;&#x7a;&#104;&#x79;&#x40;&#x73;&#104;&#97;&#x6e;&#103;&#x68;&#97;&#105;&#116;&#x65;&#x63;&#104;&#x2e;&#101;&#x64;&#117;&#46;&#99;&#x6e;", "mailto:&#x6c;&#x69;&#x6e;&#x7a;&#104;&#x79;&#x40;&#x73;&#104;&#97;&#x6e;&#103;&#x68;&#97;&#105;&#116;&#x65;&#x63;&#104;&#x2e;&#101;&#x64;&#117;&#46;&#99;&#x6e;"]
        ],
        "ta-courses": [
            ["Fall", "2020", "CS130", "Operating Systems I"]
        ]
    },
    "sunshuo": {
        "name": "孙硕",
        "info": [
            ["envelope", "&#x73;&#x75;&#x6e;&#x73;&#104;&#x75;&#x6f;&#64;&#115;&#x68;&#x61;&#x6e;&#103;&#104;&#x61;&#105;&#116;&#x65;&#x63;&#104;&#46;&#101;&#100;&#117;&#46;&#99;&#x6e;", "mailto:&#x73;&#x75;&#x6e;&#x73;&#104;&#x75;&#x6f;&#64;&#115;&#x68;&#x61;&#x6e;&#103;&#104;&#x61;&#105;&#116;&#x65;&#x63;&#104;&#46;&#101;&#100;&#117;&#46;&#99;&#x6e;"]
        ],
        "ta-courses": [
            ["Fall", "2020", "CS130", "Operating Systems I"]
        ]
    },
    "xuzj": {
        "name": "徐子钧",
        "info": [
            ["envelope", "&#120;&#x75;&#122;&#106;&#x40;&#x73;&#104;&#x61;&#110;&#103;&#x68;&#x61;&#x69;&#116;&#x65;&#99;&#104;&#x2e;&#101;&#100;&#117;&#x2e;&#x63;&#110;", "mailto:&#120;&#x75;&#122;&#106;&#x40;&#x73;&#104;&#x61;&#110;&#103;&#x68;&#x61;&#x69;&#116;&#x65;&#99;&#104;&#x2e;&#101;&#100;&#117;&#x2e;&#x63;&#110;"]
        ],
        "ta-courses": [
            ["Fall", "2020", "CS130", "Operating Systems I"]
        ]
    },
    "wuhp": {
        "name": "吴翰培",
        "image": "https://ghproxy.com/https://raw.githubusercontent.com/i-TechX/iTechX/file-base/people/images/wuhp.jpg",
        "info": [
            ["envelope", "&#119;&#x75;&#x68;&#x70;&#x40;&#x73;&#104;&#x61;&#110;&#103;&#104;&#x61;&#105;&#x74;&#x65;&#x63;&#104;&#46;&#x65;&#100;&#117;&#46;&#x63;&#x6e;", "mailto:&#119;&#x75;&#x68;&#x70;&#x40;&#x73;&#104;&#x61;&#110;&#103;&#104;&#x61;&#105;&#x74;&#x65;&#x63;&#104;&#46;&#x65;&#100;&#117;&#46;&#x63;&#x6e;"]
        ],
        "ta-courses": [
            ["Fall", "2020", "CS130", "Operating Systems I"]
        ]
    },
    "wuty": {
        "name": "吴天元",
        "image": "https://ghproxy.com/https://raw.githubusercontent.com/i-TechX/iTechX/file-base/people/images/wuty.jpg",
        "info": [
            ["envelope", "&#x77;&#x75;&#116;&#121;&#64;&#x73;&#x68;&#97;&#110;&#103;&#x68;&#97;&#x69;&#x74;&#101;&#x63;&#x68;&#46;&#x65;&#100;&#x75;&#x2e;&#x63;&#x6e;", "mailto:&#x77;&#x75;&#116;&#121;&#64;&#x73;&#x68;&#97;&#110;&#103;&#x68;&#97;&#x69;&#x74;&#101;&#x63;&#x68;&#46;&#x65;&#100;&#x75;&#x2e;&#x63;&#x6e;"]
        ],
        "ta-courses": [
            ["Fall", "2020", "CS130", "Operating Systems I"]
        ]
    },
    "zhangjian": {
        "name": "张坚",
        "info": [
            ["envelope", "&#x7a;&#x68;&#97;&#x6e;&#103;&#106;&#x69;&#x61;&#x6e;&#64;&#x73;&#x68;&#x61;&#110;&#x67;&#104;&#97;&#105;&#x74;&#x65;&#99;&#x68;&#46;&#x65;&#100;&#117;&#x2e;&#99;&#x6e;", "mailto:&#x7a;&#x68;&#97;&#x6e;&#103;&#106;&#x69;&#x61;&#x6e;&#64;&#x73;&#x68;&#x61;&#110;&#x67;&#104;&#97;&#105;&#x74;&#x65;&#99;&#x68;&#46;&#x65;&#100;&#117;&#x2e;&#99;&#x6e;"]
        ],
        "ta-courses": [
            ["Fall", "2020", "CS130", "Operating Systems I"],
            ["Fall", "2019", "CS130", "Operating Systems I"]
        ]
    },
    "jingyzh": {
        "name": "荆玉琢",
        "image": "https://ghproxy.com/https://raw.githubusercontent.com/i-TechX/iTechX/file-base/people/images/jingyzh.jpg",
        "info": [
            ["envelope", "&#106;&#x69;&#110;&#103;&#121;&#x7a;&#x68;&#64;&#115;&#x68;&#97;&#x6e;&#x67;&#104;&#97;&#105;&#116;&#101;&#x63;&#104;&#x2e;&#x65;&#100;&#117;&#46;&#x63;&#110;", "mailto:&#106;&#x69;&#110;&#103;&#121;&#x7a;&#x68;&#64;&#115;&#x68;&#97;&#x6e;&#x67;&#104;&#97;&#105;&#116;&#101;&#x63;&#104;&#x2e;&#x65;&#100;&#117;&#46;&#x63;&#110;"]
        ],
        "ta-courses": [
            ["Fall", "2019", "CS130", "Operating Systems I"]
        ]
    },
    "jinjch": {
        "name": "金佳纯",
        "info": [
            ["envelope", "&#x6a;&#x69;&#x6e;&#106;&#x63;&#x68;&#64;&#x73;&#104;&#97;&#110;&#x67;&#104;&#x61;&#105;&#116;&#x65;&#x63;&#x68;&#46;&#101;&#100;&#117;&#x2e;&#99;&#110;", "mailto:&#x6a;&#x69;&#x6e;&#106;&#x63;&#x68;&#64;&#x73;&#104;&#97;&#110;&#x67;&#104;&#x61;&#105;&#116;&#x65;&#x63;&#x68;&#46;&#101;&#100;&#117;&#x2e;&#99;&#110;"]
        ],
        "ta-courses": [
            ["Fall", "2019", "CS130", "Operating Systems I"]
        ]
    },
    "yechn": {
        "name": "叶崇南",
        "image": "https://ghproxy.com/https://raw.githubusercontent.com/i-TechX/iTechX/file-base/people/images/yechn.jpg",
        "info": [
            ["envelope", "&#x79;&#101;&#x63;&#x68;&#x6e;&#64;&#115;&#x68;&#97;&#110;&#x67;&#x68;&#x61;&#x69;&#x74;&#101;&#99;&#x68;&#46;&#101;&#100;&#117;&#x2e;&#99;&#110;", "mailto:&#x79;&#101;&#x63;&#x68;&#x6e;&#64;&#115;&#x68;&#97;&#110;&#x67;&#x68;&#x61;&#x69;&#x74;&#101;&#99;&#x68;&#46;&#101;&#100;&#117;&#x2e;&#99;&#110;"]
        ],
        "ta-courses": [
            ["Fall", "2019", "CS130", "Operating Systems I"]
        ]
    },
    "wangyh1": {
        "name": "王奕涵",
        "image": "https://ghproxy.com/https://raw.githubusercontent.com/i-TechX/iTechX/file-base/people/images/wangyh1.jpg",
        "info": [
            ["envelope", "&#119;&#97;&#x6e;&#x67;&#121;&#104;&#49;&#x40;&#115;&#104;&#97;&#x6e;&#x67;&#104;&#x61;&#105;&#116;&#x65;&#99;&#104;&#x2e;&#x65;&#100;&#117;&#46;&#x63;&#x6e;", "mailto:&#119;&#97;&#x6e;&#x67;&#121;&#104;&#49;&#x40;&#115;&#104;&#97;&#x6e;&#x67;&#104;&#x61;&#105;&#116;&#x65;&#99;&#104;&#x2e;&#x65;&#100;&#117;&#46;&#x63;&#x6e;"]
        ],
        "ta-courses": [
            ["Fall", "2019", "CS130", "Operating Systems I"]
        ]
    },
    "yangzhj": {
        "name": "杨之杰",
        "image": "https://ghproxy.com/https://raw.githubusercontent.com/i-TechX/iTechX/file-base/people/images/yangzhj.jpg",
        "info": [
            ["envelope", "&#x79;&#97;&#x6e;&#103;&#122;&#104;&#106;&#64;&#115;&#x68;&#x61;&#110;&#103;&#104;&#97;&#105;&#116;&#101;&#99;&#x68;&#x2e;&#x65;&#x64;&#117;&#46;&#99;&#110;", "mailto:&#x79;&#97;&#x6e;&#103;&#122;&#104;&#106;&#64;&#115;&#x68;&#x61;&#110;&#103;&#104;&#97;&#105;&#116;&#101;&#99;&#x68;&#x2e;&#x65;&#x64;&#117;&#46;&#99;&#110;"]
        ],
        "ta-courses": [
            ["Fall", "2019", "CS130", "Operating Systems I"]
        ]
    },
    "dengtl": {
        "name": "邓通亮",
        "image": "https://ghproxy.com/https://raw.githubusercontent.com/i-TechX/iTechX/file-base/people/images/dengtl.jpg",
        "info": [
            ["envelope", "&#100;&#x65;&#110;&#x67;&#x74;&#108;&#64;&#115;&#104;&#97;&#x6e;&#x67;&#x68;&#97;&#105;&#116;&#101;&#99;&#104;&#46;&#101;&#100;&#117;&#x2e;&#x63;&#110;", "mailto:&#100;&#x65;&#110;&#x67;&#x74;&#108;&#64;&#115;&#104;&#97;&#x6e;&#x67;&#x68;&#97;&#105;&#116;&#101;&#99;&#104;&#46;&#101;&#100;&#117;&#x2e;&#x63;&#110;"]
        ],
        "ta-courses": [
            ["Fall", "2019", "CS130", "Operating Systems I"],
            ["Fall", "2018", "CS130", "Operating Systems I"]
        ]
    },
    "xiezhq": {
        "name": "谢志强",
        "image": "https://ghproxy.com/https://raw.githubusercontent.com/i-TechX/iTechX/file-base/people/images/xiezhq.jpg",
        "info": [
            ["envelope", "&#x78;&#x69;&#101;&#x7a;&#x68;&#x71;&#x40;&#x73;&#104;&#x61;&#110;&#x67;&#x68;&#x61;&#x69;&#x74;&#x65;&#99;&#104;&#46;&#101;&#x64;&#x75;&#x2e;&#x63;&#x6e;", "mailto:&#x78;&#x69;&#101;&#x7a;&#x68;&#x71;&#x40;&#x73;&#104;&#x61;&#110;&#x67;&#x68;&#x61;&#x69;&#x74;&#x65;&#99;&#104;&#46;&#101;&#x64;&#x75;&#x2e;&#x63;&#x6e;"]
        ],
        "ta-courses": [
            ["Fall", "2019", "CS130", "Operating Systems I"]
        ]
    },
    "zouyl": {
        "name": "邹彦良",
        "image": "https://ghproxy.com/https://raw.githubusercontent.com/i-TechX/iTechX/file-base/people/images/zouyl.jpg",
        "info": [
            ["envelope", "&#x7a;&#x6f;&#x75;&#121;&#108;&#x40;&#115;&#104;&#97;&#110;&#x67;&#x68;&#97;&#x69;&#x74;&#x65;&#99;&#104;&#x2e;&#x65;&#100;&#117;&#46;&#x63;&#110;", "mailto:&#x7a;&#x6f;&#x75;&#121;&#108;&#x40;&#115;&#104;&#97;&#110;&#x67;&#x68;&#97;&#x69;&#x74;&#x65;&#99;&#104;&#x2e;&#x65;&#100;&#117;&#46;&#x63;&#110;"]
        ],
        "ta-courses": [
            ["Fall", "2018", "CS130", "Operating Systems I"]
        ]
    },
    "chenchen": {
        "name": "陈宸",
        "image": "https://ghproxy.com/https://raw.githubusercontent.com/i-TechX/iTechX/file-base/people/images/chenchen.jpg",
        "info": [
            ["envelope", "&#x63;&#x68;&#101;&#x6e;&#x63;&#x68;&#101;&#110;&#x40;&#115;&#x68;&#97;&#110;&#103;&#x68;&#97;&#105;&#x74;&#x65;&#x63;&#x68;&#x2e;&#x65;&#x64;&#117;&#46;&#x63;&#x6e;", "mailto:&#x63;&#x68;&#101;&#x6e;&#x63;&#x68;&#101;&#110;&#x40;&#115;&#x68;&#97;&#110;&#103;&#x68;&#97;&#105;&#x74;&#x65;&#x63;&#x68;&#x2e;&#x65;&#x64;&#117;&#46;&#x63;&#x6e;"]
        ],
        "ta-courses": [
            ["Fall", "2018", "CS130", "Operating Systems I"]
        ]
    },
    "luohc": {
        "name": "罗浩聪",
        "info": [
            ["envelope", "&#x6c;&#117;&#111;&#x68;&#99;&#64;&#115;&#104;&#x61;&#x6e;&#103;&#104;&#97;&#105;&#116;&#x65;&#x63;&#104;&#46;&#101;&#x64;&#117;&#x2e;&#x63;&#x6e;", "mailto:&#x6c;&#117;&#111;&#x68;&#99;&#64;&#115;&#104;&#x61;&#x6e;&#103;&#104;&#97;&#105;&#116;&#x65;&#x63;&#104;&#46;&#101;&#x64;&#117;&#x2e;&#x63;&#x6e;"]
        ],
        "ta-courses": [
            ["Fall", "2018", "CS130", "Operating Systems I"]
        ]
    },
    "nianzhl": {
        "name": "念中林",
        "image": "https://ghproxy.com/https://raw.githubusercontent.com/i-TechX/iTechX/file-base/people/images/nianzhl.jpg",
        "info": [
            ["envelope", "&#x6e;&#105;&#x61;&#x6e;&#x7a;&#104;&#x6c;&#x40;&#x73;&#104;&#97;&#110;&#x67;&#x68;&#x61;&#105;&#x74;&#101;&#99;&#x68;&#x2e;&#x65;&#100;&#117;&#46;&#x63;&#x6e;", "mailto:&#x6e;&#105;&#x61;&#x6e;&#x7a;&#104;&#x6c;&#x40;&#x73;&#104;&#97;&#110;&#x67;&#x68;&#x61;&#105;&#x74;&#101;&#99;&#x68;&#x2e;&#x65;&#100;&#117;&#46;&#x63;&#x6e;"]
        ],
        "ta-courses": [
            ["Fall", "2018", "CS130", "Operating Systems I"]
        ]
    },
    "hugzh1": {
        "name": "胡冠洲",
        "info": [
            ["envelope", "&#x68;&#x75;&#x67;&#x7a;&#104;&#49;&#64;&#x73;&#x68;&#x61;&#x6e;&#x67;&#104;&#97;&#x69;&#116;&#x65;&#x63;&#x68;&#46;&#101;&#x64;&#x75;&#x2e;&#99;&#110;", "mailto:&#x68;&#x75;&#x67;&#x7a;&#104;&#49;&#64;&#x73;&#x68;&#x61;&#x6e;&#x67;&#104;&#97;&#x69;&#116;&#x65;&#x63;&#x68;&#46;&#101;&#x64;&#x75;&#x2e;&#99;&#110;"],
            ["home", "Home Page", "josehu.com"]
        ],
        "ta-courses": [
            ["Fall", "2018", "CS130", "Operating Systems I"]
        ]
    }
}